OneNeuron/__init__.py
OneNeuron/perceptron.py
keithferns98_OneNeuron-0.0.1.dist-info/LICENSE
keithferns98_OneNeuron-0.0.1.dist-info/METADATA
keithferns98_OneNeuron-0.0.1.dist-info/WHEEL
keithferns98_OneNeuron-0.0.1.dist-info/top_level.txt
keithferns98_OneNeuron-0.0.1.dist-info/RECORD
